{"v":"5.0.4","fr":60,"ip":0,"op":121,"w":360,"h":128,"ddd":0,"assets":[],"layers":[{"ddd":0,"ind":1,"ty":4,"sr":1,"ks":{"o":{"a":0,"k":100,"ix":11},"r":{"a":1,"k":[{"i":{"x":[0.2],"y":[1]},"o":{"x":[0.4],"y":[0]},"n":["0p2_1_0p4_0"],"t":10,"s":[0],"e":[8]},{"i":{"x":[0.2],"y":[1]},"o":{"x":[0.4],"y":[0]},"n":["0p2_1_0p4_0"],"t":25,"s":[8],"e":[8]},{"i":{"x":[0.2],"y":[1]},"o":{"x":[0.4],"y":[0]},"n":["0p2_1_0p4_0"],"t":85,"s":[8],"e":[0]},{"t":100}],"ix":10},"p":{"a":1,"k":[{"i":{"x":0.2,"y":1},"o":{"x":0.4,"y":0},"n":"0p2_1_0p4_0","t":10,"s":[182.5,52,0],"e":[192.5,55,0],"to":[1.66666662693024,0.5,0],"ti":[-1.66666662693024,-0.5,0]},{"i":{"x":0.531,"y":0.531},"o":{"x":0.576,"y":0.576},"n":"0p531_0p531_0p576_0p576","t":25,"s":[192.5,55,0],"e":[192.5,55,0],"to":[0,0,0],"ti":[0,0,0]},{"i":{"x":0.2,"y":1},"o":{"x":0.4,"y":0},"n":"0p2_1_0p4_0","t":85,"s":[192.5,55,0],"e":[182.5,52,0],"to":[-1.66666662693024,-0.5,0],"ti":[1.66666662693024,0.5,0]},{"t":100}],"ix":2},"a":{"a":0,"k":[2.55,-14.503,0],"ix":1},"s":{"a":0,"k":[100,100,100],"ix":6}},"ao":0,"shapes":[{"ty":"gr","it":[{"ind":0,"ty":"sh","ix":1,"ks":{"a":0,"k":{"i":[[0.5,0],[0.1,-0.5],[3.8,0],[0,0.4],[0.5,0],[0,-0.5],[-4.4,0],[-0.1,1.8]],"o":[[-0.5,0],[0,0.1],[-3.7,0],[0,-0.5],[-0.5,0],[0.1,1.8],[4.4,0],[0.2,-0.5]],"v":[[6.4,-22.2],[5.4,-21.3],[1.4,-17.8],[-2.6,-21.3],[-3.6,-22.2],[-4.5,-21.2],[1.3,-16],[7.1,-21.2]],"c":true},"ix":2},"hd":false},{"ty":"fl","c":{"a":0,"k":[0.258823543787,0.521568655968,0.956862747669,1],"ix":4},"o":{"a":0,"k":100,"ix":5},"r":1,"hd":false},{"ty":"tr","p":{"a":0,"k":[0,0],"ix":2},"a":{"a":0,"k":[0,0],"ix":1},"s":{"a":0,"k":[100,100],"ix":3},"r":{"a":0,"k":0,"ix":6},"o":{"a":0,"k":100,"ix":7},"sk":{"a":0,"k":0,"ix":4},"sa":{"a":0,"k":0,"ix":5}}],"np":2,"cix":2,"ix":1,"hd":false},{"ty":"gr","it":[{"d":1,"ty":"el","s":{"a":1,"k":[{"i":{"x":[0.2,0.2],"y":[1,1]},"o":{"x":[0.4,0.4],"y":[0,0]},"n":["0p2_1_0p4_0","0p2_1_0p4_0"],"t":40,"s":[5.4,5.4],"e":[6.4,2.4]},{"i":{"x":[0.2,0.2],"y":[1,1]},"o":{"x":[0.4,0.4],"y":[0,0]},"n":["0p2_1_0p4_0","0p2_1_0p4_0"],"t":50,"s":[6.4,2.4],"e":[6.4,2.4]},{"i":{"x":[0.2,0.2],"y":[1,1]},"o":{"x":[0.4,0.4],"y":[0,0]},"n":["0p2_1_0p4_0","0p2_1_0p4_0"],"t":85,"s":[6.4,2.4],"e":[5.4,5.4]},{"t":100}],"ix":2},"p":{"a":0,"k":[0,0],"ix":3},"hd":false},{"ty":"fl","c":{"a":0,"k":[0.258823543787,0.521568655968,0.956862747669,1],"ix":4},"o":{"a":0,"k":100,"ix":5},"r":1,"hd":false},{"ty":"tr","p":{"a":0,"k":[-6.2,-27],"ix":2},"a":{"a":0,"k":[0,0],"ix":1},"s":{"a":0,"k":[100,100],"ix":3},"r":{"a":0,"k":0,"ix":6},"o":{"a":0,"k":100,"ix":7},"sk":{"a":0,"k":0,"ix":4},"sa":{"a":0,"k":0,"ix":5}}],"np":2,"cix":2,"ix":2,"hd":false},{"ty":"gr","it":[{"d":1,"ty":"el","s":{"a":1,"k":[{"i":{"x":[0.2,0.2],"y":[1,1]},"o":{"x":[0.4,0.4],"y":[0,0]},"n":["0p2_1_0p4_0","0p2_1_0p4_0"],"t":40,"s":[5.4,5.4],"e":[6.4,2.4]},{"i":{"x":[0.2,0.2],"y":[1,1]},"o":{"x":[0.4,0.4],"y":[0,0]},"n":["0p2_1_0p4_0","0p2_1_0p4_0"],"t":50,"s":[6.4,2.4],"e":[6.4,2.4]},{"i":{"x":[0.2,0.2],"y":[1,1]},"o":{"x":[0.4,0.4],"y":[0,0]},"n":["0p2_1_0p4_0","0p2_1_0p4_0"],"t":85,"s":[6.4,2.4],"e":[5.4,5.4]},{"t":100}],"ix":2},"p":{"a":0,"k":[0,0],"ix":3},"hd":false},{"ty":"fl","c":{"a":0,"k":[0.258823543787,0.521568655968,0.956862747669,1],"ix":4},"o":{"a":0,"k":100,"ix":5},"r":1,"hd":false},{"ty":"tr","p":{"a":0,"k":[7.2,-27],"ix":2},"a":{"a":0,"k":[0,0],"ix":1},"s":{"a":0,"k":[100,100],"ix":3},"r":{"a":0,"k":0,"ix":6},"o":{"a":0,"k":100,"ix":7},"sk":{"a":0,"k":0,"ix":4},"sa":{"a":0,"k":0,"ix":5}}],"np":2,"cix":2,"ix":3,"hd":false}],"ip":0,"op":121,"st":0,"bm":0},{"ddd":0,"ind":2,"ty":4,"sr":1,"ks":{"o":{"a":0,"k":100,"ix":11},"r":{"a":1,"k":[{"i":{"x":[0.2],"y":[1]},"o":{"x":[0.4],"y":[0]},"n":["0p2_1_0p4_0"],"t":10,"s":[0],"e":[16]},{"i":{"x":[0.569],"y":[1]},"o":{"x":[0.576],"y":[0]},"n":["0p569_1_0p576_0"],"t":25,"s":[16],"e":[16]},{"i":{"x":[0.2],"y":[1]},"o":{"x":[0.4],"y":[0]},"n":["0p2_1_0p4_0"],"t":85,"s":[16],"e":[0]},{"t":100}],"ix":10},"p":{"a":1,"k":[{"i":{"x":0.2,"y":1},"o":{"x":0.4,"y":0},"n":"0p2_1_0p4_0","t":10,"s":[181.5,30.5,0],"e":[191.5,32.5,0],"to":[1.66666662693024,0.33333334326744,0],"ti":[-1.66666662693024,-0.33333334326744,0]},{"i":{"x":0.569,"y":0.569},"o":{"x":0.576,"y":0.576},"n":"0p569_0p569_0p576_0p576","t":25,"s":[191.5,32.5,0],"e":[191.5,32.5,0],"to":[0,0,0],"ti":[0,0,0]},{"i":{"x":0.2,"y":1},"o":{"x":0.4,"y":0},"n":"0p2_1_0p4_0","t":85,"s":[191.5,32.5,0],"e":[181.5,30.5,0],"to":[-1.66666662693024,-0.33333334326744,0],"ti":[1.66666662693024,0.33333334326744,0]},{"t":100}],"ix":2},"a":{"a":0,"k":[1.55,-36.003,0],"ix":1},"s":{"a":0,"k":[100,100,100],"ix":6}},"ao":0,"shapes":[{"ty":"gr","it":[{"ind":0,"ty":"sh","ix":1,"ks":{"a":1,"k":[{"i":{"x":0.2,"y":1},"o":{"x":0.4,"y":0},"n":"0p2_1_0p4_0","t":40,"s":[{"i":[[0,0],[0,0],[1,-1],[-1,-1],[0,0]],"o":[[0,0],[-1,-0.9],[-0.9,1],[0,0],[0,0]],"v":[[-9.125,-41.069],[-11.8,-43.5],[-15.4,-43.3],[-15.2,-39.7],[-10.688,-35.663]],"c":true}],"e":[{"i":[[0,0],[0,0],[0.593,-1.284],[-1.284,-0.593],[0,0]],"o":[[0,0],[-1.249,-0.499],[-0.499,1.249],[0,0],[0,0]],"v":[[-10.329,-41.494],[-13.679,-42.852],[-16.988,-41.421],[-15.558,-38.111],[-9.928,-35.88]],"c":true}]},{"i":{"x":0.2,"y":1},"o":{"x":0.167,"y":0},"n":"0p2_1_0p167_0","t":60,"s":[{"i":[[0,0],[0,0],[0.593,-1.284],[-1.284,-0.593],[0,0]],"o":[[0,0],[-1.249,-0.499],[-0.499,1.249],[0,0],[0,0]],"v":[[-10.329,-41.494],[-13.679,-42.852],[-16.988,-41.421],[-15.558,-38.111],[-9.928,-35.88]],"c":true}],"e":[{"i":[[0,0],[0,0],[0.593,-1.284],[-1.284,-0.593],[0,0]],"o":[[0,0],[-1.249,-0.499],[-0.499,1.249],[0,0],[0,0]],"v":[[-10.329,-41.494],[-13.679,-42.852],[-16.988,-41.421],[-15.558,-38.111],[-9.928,-35.88]],"c":true}]},{"i":{"x":0.2,"y":1},"o":{"x":0.4,"y":0},"n":"0p2_1_0p4_0","t":85,"s":[{"i":[[0,0],[0,0],[0.593,-1.284],[-1.284,-0.593],[0,0]],"o":[[0,0],[-1.249,-0.499],[-0.499,1.249],[0,0],[0,0]],"v":[[-10.329,-41.494],[-13.679,-42.852],[-16.988,-41.421],[-15.558,-38.111],[-9.928,-35.88]],"c":true}],"e":[{"i":[[0,0],[0,0],[1,-1],[-1,-1],[0,0]],"o":[[0,0],[-1,-0.9],[-0.9,1],[0,0],[0,0]],"v":[[-9.125,-41.069],[-11.8,-43.5],[-15.4,-43.3],[-15.2,-39.7],[-10.688,-35.663]],"c":true}]},{"t":95}],"ix":2},"hd":false},{"ty":"fl","c":{"a":0,"k":[0.992156863213,0.792156875134,0.250980407,1],"ix":4},"o":{"a":0,"k":100,"ix":5},"r":1,"hd":false},{"ty":"tr","p":{"a":0,"k":[0,0],"ix":2},"a":{"a":0,"k":[0,0],"ix":1},"s":{"a":0,"k":[100,100],"ix":3},"r":{"a":0,"k":0,"ix":6},"o":{"a":0,"k":100,"ix":7},"sk":{"a":0,"k":0,"ix":4},"sa":{"a":0,"k":0,"ix":5}}],"np":2,"cix":2,"ix":1,"hd":false},{"ty":"gr","it":[{"ind":0,"ty":"sh","ix":1,"ks":{"a":1,"k":[{"i":{"x":0.2,"y":1},"o":{"x":0.4,"y":0},"n":"0p2_1_0p4_0","t":40,"s":[{"i":[[0,0],[0,0],[1.2,-0.6],[-0.6,-1.2],[0,0]],"o":[[0,0],[-0.6,-1.2],[-1.2,0.6],[0,0],[0,0]],"v":[[-0.656,-47.694],[-3.2,-53.9],[-6.4,-55.2],[-7.7,-52],[-4.812,-44.788]],"c":true}],"e":[{"i":[[0,0],[0,0],[1.328,-0.188],[-0.188,-1.328],[0,0]],"o":[[0,0],[-0.188,-1.328],[-1.328,0.188],[0,0],[0,0]],"v":[[0.019,-42.679],[-0.421,-49.372],[-3.042,-51.622],[-5.291,-49.001],[-4.845,-41.244]],"c":true}]},{"i":{"x":0.2,"y":1},"o":{"x":0.167,"y":0},"n":"0p2_1_0p167_0","t":55,"s":[{"i":[[0,0],[0,0],[1.328,-0.188],[-0.188,-1.328],[0,0]],"o":[[0,0],[-0.188,-1.328],[-1.328,0.188],[0,0],[0,0]],"v":[[0.019,-42.679],[-0.421,-49.372],[-3.042,-51.622],[-5.291,-49.001],[-4.845,-41.244]],"c":true}],"e":[{"i":[[0,0],[0,0],[1.328,-0.188],[-0.188,-1.328],[0,0]],"o":[[0,0],[-0.188,-1.328],[-1.328,0.188],[0,0],[0,0]],"v":[[0.019,-42.679],[-0.421,-49.372],[-3.042,-51.622],[-5.291,-49.001],[-4.845,-41.244]],"c":true}]},{"i":{"x":0.2,"y":1},"o":{"x":0.167,"y":0},"n":"0p2_1_0p167_0","t":85,"s":[{"i":[[0,0],[0,0],[1.328,-0.188],[-0.188,-1.328],[0,0]],"o":[[0,0],[-0.188,-1.328],[-1.328,0.188],[0,0],[0,0]],"v":[[0.019,-42.679],[-0.421,-49.372],[-3.042,-51.622],[-5.291,-49.001],[-4.845,-41.244]],"c":true}],"e":[{"i":[[0,0],[0,0],[1.2,-0.6],[-0.6,-1.2],[0,0]],"o":[[0,0],[-0.6,-1.2],[-1.2,0.6],[0,0],[0,0]],"v":[[-0.656,-47.694],[-3.2,-53.9],[-6.4,-55.2],[-7.7,-52],[-4.812,-44.788]],"c":true}]},{"t":95}],"ix":2},"hd":false},{"ty":"fl","c":{"a":0,"k":[0.992156863213,0.792156875134,0.250980407,1],"ix":4},"o":{"a":0,"k":100,"ix":5},"r":1,"hd":false},{"ty":"tr","p":{"a":0,"k":[0,0],"ix":2},"a":{"a":0,"k":[0,0],"ix":1},"s":{"a":0,"k":[100,100],"ix":3},"r":{"a":0,"k":0,"ix":6},"o":{"a":0,"k":100,"ix":7},"sk":{"a":0,"k":0,"ix":4},"sa":{"a":0,"k":0,"ix":5}}],"np":2,"cix":2,"ix":2,"hd":false},{"ty":"gr","it":[{"ind":0,"ty":"sh","ix":1,"ks":{"a":1,"k":[{"i":{"x":0.2,"y":1},"o":{"x":0.167,"y":0},"n":"0p2_1_0p167_0","t":40,"s":[{"i":[[0,0],[0,0.5],[0,0],[-0.1,0.3],[-0.3,-0.1],[-0.5,-3],[0.4,0]],"o":[[-0.3,0],[-0.4,-2.1],[-0.4,-0.2],[0.2,-0.4],[0.1,0],[0.1,0.5],[0.1,0]],"v":[[10.7,-39.7],[10,-40.4],[7.9,-43],[7.4,-43.9],[8.3,-44.4],[11.3,-40.6],[10.7,-39.7]],"c":true}],"e":[{"i":[[0,0],[0,0.5],[0,0],[-0.1,0.3],[-0.3,-0.1],[-0.5,-3],[0.4,0]],"o":[[-0.3,0],[-0.4,-2.1],[-0.4,-0.2],[0.2,-0.4],[0.1,0],[0.1,0.5],[0.1,0]],"v":[[10.7,-39.7],[10,-40.4],[7.9,-43],[7.4,-43.9],[8.3,-44.4],[11.3,-40.6],[10.7,-39.7]],"c":true}]},{"t":95}],"ix":2},"hd":false},{"ty":"fl","c":{"a":0,"k":[0.992156863213,0.792156875134,0.250980407,1],"ix":4},"o":{"a":0,"k":100,"ix":5},"r":1,"hd":false},{"ty":"tr","p":{"a":0,"k":[0,0],"ix":2},"a":{"a":0,"k":[0,0],"ix":1},"s":{"a":0,"k":[100,100],"ix":3},"r":{"a":0,"k":0,"ix":6},"o":{"a":0,"k":100,"ix":7},"sk":{"a":0,"k":0,"ix":4},"sa":{"a":0,"k":0,"ix":5}}],"np":2,"cix":2,"ix":3,"hd":false},{"ty":"gr","it":[{"ind":0,"ty":"sh","ix":1,"ks":{"a":1,"k":[{"i":{"x":0.2,"y":1},"o":{"x":0.4,"y":0},"n":"0p2_1_0p4_0","t":40,"s":[{"i":[[0,0],[0,0],[1,0.9],[0.8,-1.1],[0,0]],"o":[[0,0],[0.9,-1],[-1.1,-0.8],[0,0],[0,0]],"v":[[11.906,-40.913],[15.8,-45.9],[15.4,-49.4],[11.9,-49],[8.25,-44.319]],"c":true}],"e":[{"i":[[0,0],[0,0],[1.287,0.391],[0.258,-1.335],[0,0]],"o":[[0,0],[0.391,-1.287],[-1.335,-0.258],[0,0],[0,0]],"v":[[12.901,-37.66],[14.312,-43.829],[12.465,-46.828],[9.465,-44.982],[8.145,-39.194]],"c":true}]},{"i":{"x":0.2,"y":1},"o":{"x":0.167,"y":0},"n":"0p2_1_0p167_0","t":55,"s":[{"i":[[0,0],[0,0],[1.287,0.391],[0.258,-1.335],[0,0]],"o":[[0,0],[0.391,-1.287],[-1.335,-0.258],[0,0],[0,0]],"v":[[12.901,-37.66],[14.312,-43.829],[12.465,-46.828],[9.465,-44.982],[8.145,-39.194]],"c":true}],"e":[{"i":[[0,0],[0,0],[1.287,0.391],[0.258,-1.335],[0,0]],"o":[[0,0],[0.391,-1.287],[-1.335,-0.258],[0,0],[0,0]],"v":[[12.901,-37.66],[14.312,-43.829],[12.465,-46.828],[9.465,-44.982],[8.145,-39.194]],"c":true}]},{"i":{"x":0.2,"y":1},"o":{"x":0.167,"y":0},"n":"0p2_1_0p167_0","t":85,"s":[{"i":[[0,0],[0,0],[1.287,0.391],[0.258,-1.335],[0,0]],"o":[[0,0],[0.391,-1.287],[-1.335,-0.258],[0,0],[0,0]],"v":[[12.901,-37.66],[14.312,-43.829],[12.465,-46.828],[9.465,-44.982],[8.145,-39.194]],"c":true}],"e":[{"i":[[0,0],[0,0],[1,0.9],[0.8,-1.1],[0,0]],"o":[[0,0],[0.9,-1],[-1.1,-0.8],[0,0],[0,0]],"v":[[11.906,-40.913],[15.8,-45.9],[15.4,-49.4],[11.9,-49],[8.25,-44.319]],"c":true}]},{"t":95}],"ix":2},"hd":false},{"ty":"fl","c":{"a":0,"k":[0.992156863213,0.792156875134,0.250980407,1],"ix":4},"o":{"a":0,"k":100,"ix":5},"r":1,"hd":false},{"ty":"tr","p":{"a":0,"k":[0,0],"ix":2},"a":{"a":0,"k":[0,0],"ix":1},"s":{"a":0,"k":[100,100],"ix":3},"r":{"a":0,"k":0,"ix":6},"o":{"a":0,"k":100,"ix":7},"sk":{"a":0,"k":0,"ix":4},"sa":{"a":0,"k":0,"ix":5}}],"np":2,"cix":2,"ix":4,"hd":false},{"ty":"gr","it":[{"ind":0,"ty":"sh","ix":1,"ks":{"a":1,"k":[{"i":{"x":0.2,"y":1},"o":{"x":0.4,"y":0},"n":"0p2_1_0p4_0","t":40,"s":[{"i":[[0,0],[0,0],[1.3,0.4],[0.4,-1.3],[0,0]],"o":[[0,0],[0.4,-1.3],[-1.3,-0.4],[0,0],[0,0]],"v":[[8.562,-44.631],[10.7,-51.7],[9,-54.8],[5.9,-53.1],[4.062,-46.538]],"c":true}],"e":[{"i":[[0,0],[0,0],[1.328,0.294],[0.294,-1.328],[0,0]],"o":[[0,0],[0.294,-1.328],[-1.328,-0.294],[0,0],[0,0]],"v":[[8.561,-39.918],[10.12,-47.136],[8.175,-50.089],[5.223,-48.144],[3.922,-41.454]],"c":true}]},{"i":{"x":0.2,"y":1},"o":{"x":0.167,"y":0},"n":"0p2_1_0p167_0","t":55,"s":[{"i":[[0,0],[0,0],[1.328,0.294],[0.294,-1.328],[0,0]],"o":[[0,0],[0.294,-1.328],[-1.328,-0.294],[0,0],[0,0]],"v":[[8.561,-39.918],[10.12,-47.136],[8.175,-50.089],[5.223,-48.144],[3.922,-41.454]],"c":true}],"e":[{"i":[[0,0],[0,0],[1.328,0.294],[0.294,-1.328],[0,0]],"o":[[0,0],[0.294,-1.328],[-1.328,-0.294],[0,0],[0,0]],"v":[[8.561,-39.918],[10.12,-47.136],[8.175,-50.089],[5.223,-48.144],[3.922,-41.454]],"c":true}]},{"i":{"x":0.2,"y":1},"o":{"x":0.167,"y":0},"n":"0p2_1_0p167_0","t":85,"s":[{"i":[[0,0],[0,0],[1.328,0.294],[0.294,-1.328],[0,0]],"o":[[0,0],[0.294,-1.328],[-1.328,-0.294],[0,0],[0,0]],"v":[[8.561,-39.918],[10.12,-47.136],[8.175,-50.089],[5.223,-48.144],[3.922,-41.454]],"c":true}],"e":[{"i":[[0,0],[0,0],[1.3,0.4],[0.4,-1.3],[0,0]],"o":[[0,0],[0.4,-1.3],[-1.3,-0.4],[0,0],[0,0]],"v":[[8.562,-44.631],[10.7,-51.7],[9,-54.8],[5.9,-53.1],[4.062,-46.538]],"c":true}]},{"t":95}],"ix":2},"hd":false},{"ty":"fl","c":{"a":0,"k":[0.992156863213,0.792156875134,0.250980407,1],"ix":4},"o":{"a":0,"k":100,"ix":5},"r":1,"hd":false},{"ty":"tr","p":{"a":0,"k":[0,0],"ix":2},"a":{"a":0,"k":[0,0],"ix":1},"s":{"a":0,"k":[100,100],"ix":3},"r":{"a":0,"k":0,"ix":6},"o":{"a":0,"k":100,"ix":7},"sk":{"a":0,"k":0,"ix":4},"sa":{"a":0,"k":0,"ix":5}}],"np":2,"cix":2,"ix":5,"hd":false},{"ty":"gr","it":[{"ind":0,"ty":"sh","ix":1,"ks":{"a":1,"k":[{"i":{"x":0.2,"y":1},"o":{"x":0.167,"y":0},"n":"0p2_1_0p167_0","t":40,"s":[{"i":[[0,0],[7.157,0],[0,-7.157]],"o":[[0,-7.157],[-7.157,0],[0,0]],"v":[[14.219,-35.42],[1.259,-48.38],[-11.7,-35.42]],"c":true}],"e":[{"i":[[0,0],[7.157,0],[0,-7.157]],"o":[[0,-7.157],[-7.157,0],[0,0]],"v":[[14.219,-35.42],[1.259,-48.38],[-11.7,-35.42]],"c":true}]},{"t":95}],"ix":2},"hd":false},{"ty":"fl","c":{"a":0,"k":[0.992156863213,0.792156875134,0.250980407,1],"ix":4},"o":{"a":0,"k":100,"ix":5},"r":1,"hd":false},{"ty":"tr","p":{"a":0,"k":[0,0],"ix":2},"a":{"a":0,"k":[0,0],"ix":1},"s":{"a":0,"k":[100,100],"ix":3},"r":{"a":0,"k":0,"ix":6},"o":{"a":0,"k":100,"ix":7},"sk":{"a":0,"k":0,"ix":4},"sa":{"a":0,"k":0,"ix":5}}],"np":2,"cix":2,"ix":6,"hd":false},{"ty":"gr","it":[{"ind":0,"ty":"sh","ix":1,"ks":{"a":1,"k":[{"i":{"x":0.2,"y":1},"o":{"x":0.4,"y":0},"n":"0p2_1_0p4_0","t":40,"s":[{"i":[[0,0],[0,0],[1.5,0.1],[0.1,-1.5],[0,0]],"o":[[0,0],[0.1,-1.3],[-1.5,-0.1],[0,0],[0,0]],"v":[[3.75,-46.153],[4.1,-54.4],[1.7,-57],[-0.9,-54.6],[-1.25,-46.944]],"c":true}],"e":[{"i":[[0,0],[0,0],[1.5,0.1],[0.1,-1.5],[0,0]],"o":[[0,0],[0.1,-1.3],[-1.5,-0.1],[0,0],[0,0]],"v":[[4.66,-41.498],[5.01,-49.745],[2.61,-52.345],[0.01,-49.945],[-0.34,-42.289]],"c":true}]},{"i":{"x":0.2,"y":1},"o":{"x":0.167,"y":0},"n":"0p2_1_0p167_0","t":55,"s":[{"i":[[0,0],[0,0],[1.5,0.1],[0.1,-1.5],[0,0]],"o":[[0,0],[0.1,-1.3],[-1.5,-0.1],[0,0],[0,0]],"v":[[4.66,-41.498],[5.01,-49.745],[2.61,-52.345],[0.01,-49.945],[-0.34,-42.289]],"c":true}],"e":[{"i":[[0,0],[0,0],[1.5,0.1],[0.1,-1.5],[0,0]],"o":[[0,0],[0.1,-1.3],[-1.5,-0.1],[0,0],[0,0]],"v":[[4.66,-41.498],[5.01,-49.745],[2.61,-52.345],[0.01,-49.945],[-0.34,-42.289]],"c":true}]},{"i":{"x":0.2,"y":1},"o":{"x":0.167,"y":0},"n":"0p2_1_0p167_0","t":85,"s":[{"i":[[0,0],[0,0],[1.5,0.1],[0.1,-1.5],[0,0]],"o":[[0,0],[0.1,-1.3],[-1.5,-0.1],[0,0],[0,0]],"v":[[4.66,-41.498],[5.01,-49.745],[2.61,-52.345],[0.01,-49.945],[-0.34,-42.289]],"c":true}],"e":[{"i":[[0,0],[0,0],[1.5,0.1],[0.1,-1.5],[0,0]],"o":[[0,0],[0.1,-1.3],[-1.5,-0.1],[0,0],[0,0]],"v":[[3.75,-46.153],[4.1,-54.4],[1.7,-57],[-0.9,-54.6],[-1.25,-46.944]],"c":true}]},{"t":95}],"ix":2},"hd":false},{"ty":"fl","c":{"a":0,"k":[1,0.835294127464,0.309803932905,1],"ix":4},"o":{"a":0,"k":100,"ix":5},"r":1,"hd":false},{"ty":"tr","p":{"a":0,"k":[0,0],"ix":2},"a":{"a":0,"k":[0,0],"ix":1},"s":{"a":0,"k":[100,100],"ix":3},"r":{"a":0,"k":0,"ix":6},"o":{"a":0,"k":100,"ix":7},"sk":{"a":0,"k":0,"ix":4},"sa":{"a":0,"k":0,"ix":5}}],"np":2,"cix":2,"ix":7,"hd":false}],"ip":0,"op":121,"st":0,"bm":0},{"ddd":0,"ind":3,"ty":4,"sr":1,"ks":{"o":{"a":0,"k":100,"ix":11},"r":{"a":0,"k":0,"ix":10},"p":{"a":0,"k":[215.75,59.25,0],"ix":2},"a":{"a":0,"k":[35.8,-7.253,0],"ix":1},"s":{"a":0,"k":[100,100,100],"ix":6}},"ao":0,"shapes":[{"ty":"gr","it":[{"ind":0,"ty":"sh","ix":1,"ks":{"a":1,"k":[{"i":{"x":0.2,"y":1},"o":{"x":0.4,"y":0},"n":"0p2_1_0p4_0","t":10,"s":[{"i":[[2.2,3.2],[-2.2,-3.1]],"o":[[0,0],[0,0]],"v":[[37.3,-8],[38,-1.5]],"c":true}],"e":[{"i":[[1.88,3.398],[-1.89,-3.298]],"o":[[0,0],[0,0]],"v":[[39.741,-7.99],[39.809,-1.452]],"c":true}]},{"i":{"x":0.2,"y":1},"o":{"x":0.4,"y":0},"n":"0p2_1_0p4_0","t":25,"s":[{"i":[[1.88,3.398],[-1.89,-3.298]],"o":[[0,0],[0,0]],"v":[[39.741,-7.99],[39.809,-1.452]],"c":true}],"e":[{"i":[[1.88,3.398],[-1.89,-3.298]],"o":[[0,0],[0,0]],"v":[[39.741,-7.99],[39.809,-1.452]],"c":true}]},{"i":{"x":0.2,"y":1},"o":{"x":0.4,"y":0},"n":"0p2_1_0p4_0","t":85,"s":[{"i":[[1.88,3.398],[-1.89,-3.298]],"o":[[0,0],[0,0]],"v":[[39.741,-7.99],[39.809,-1.452]],"c":true}],"e":[{"i":[[2.2,3.2],[-2.2,-3.1]],"o":[[0,0],[0,0]],"v":[[37.3,-8],[38,-1.5]],"c":true}]},{"t":100}],"ix":2},"hd":false},{"ty":"fl","c":{"a":0,"k":[0.819607913494,0.886274576187,0.992156922817,1],"ix":4},"o":{"a":0,"k":100,"ix":5},"r":1,"hd":false},{"ty":"tr","p":{"a":0,"k":[0,0],"ix":2},"a":{"a":0,"k":[0,0],"ix":1},"s":{"a":0,"k":[100,100],"ix":3},"r":{"a":0,"k":0,"ix":6},"o":{"a":0,"k":100,"ix":7},"sk":{"a":0,"k":0,"ix":4},"sa":{"a":0,"k":0,"ix":5}}],"np":2,"cix":2,"ix":1,"hd":false},{"ty":"gr","it":[{"ind":0,"ty":"sh","ix":1,"ks":{"a":0,"k":{"i":[[-1.3,0],[0,0],[0,1.2],[0,0],[1.2,0],[0,0],[0,-1.2],[0,0]],"o":[[0,0],[1.3,0],[0,0],[0,-1.3],[0,0],[-1.3,0],[0,0],[-0.1,1.3]],"v":[[28.8,24.7],[49.1,24.7],[51.4,22.4],[51.4,21.8],[49.1,19.5],[28.8,19.5],[26.5,21.8],[26.5,22.4]],"c":true},"ix":2},"hd":false},{"ty":"fl","c":{"a":0,"k":[0.258823543787,0.521568655968,0.956862747669,1],"ix":4},"o":{"a":0,"k":100,"ix":5},"r":1,"hd":false},{"ty":"tr","p":{"a":0,"k":[0,0],"ix":2},"a":{"a":0,"k":[0,0],"ix":1},"s":{"a":0,"k":[100,100],"ix":3},"r":{"a":0,"k":0,"ix":6},"o":{"a":0,"k":100,"ix":7},"sk":{"a":0,"k":0,"ix":4},"sa":{"a":0,"k":0,"ix":5}}],"np":2,"cix":2,"ix":2,"hd":false},{"ty":"gr","it":[{"ind":0,"ty":"sh","ix":1,"ks":{"a":0,"k":{"i":[[0,0],[0,0],[0,0],[1.2,0],[0,0],[0,-1.2],[0,0]],"o":[[0,0],[0,0],[0,-1.2],[0,0],[-1.2,0],[0,0],[0,0]],"v":[[28.8,19.4],[47.6,19.4],[47.6,18.1],[45.4,15.9],[31.1,15.9],[28.9,18.1],[28.9,19.4]],"c":true},"ix":2},"hd":false},{"ty":"fl","c":{"a":0,"k":[0.160784319043,0.176470592618,0.20000000298,1],"ix":4},"o":{"a":0,"k":100,"ix":5},"r":1,"hd":false},{"ty":"tr","p":{"a":0,"k":[0,0],"ix":2},"a":{"a":0,"k":[0,0],"ix":1},"s":{"a":0,"k":[100,100],"ix":3},"r":{"a":0,"k":0,"ix":6},"o":{"a":0,"k":100,"ix":7},"sk":{"a":0,"k":0,"ix":4},"sa":{"a":0,"k":0,"ix":5}}],"np":2,"cix":2,"ix":3,"hd":false},{"ty":"gr","it":[{"ind":0,"ty":"sh","ix":1,"ks":{"a":1,"k":[{"i":{"x":0.2,"y":1},"o":{"x":0.4,"y":0},"n":"0p2_1_0p4_0","t":10,"s":[{"i":[[0,0],[0,0],[1,-0.1],[-0.1,-1],[0,0]],"o":[[0,0],[-0.1,-1],[-1,0.1],[0,0],[0,0]],"v":[[40.1,17.3],[34.1,-38.3],[32.1,-39.9],[30.5,-37.9],[36.1,17.3]],"c":true}],"e":[{"i":[[0,0],[0,0],[1.005,-0.008],[-0.008,-1.005],[0,0]],"o":[[0,0],[-0.008,-1.005],[-1.005,0.008],[0,0],[0,0]],"v":[[40.219,17.373],[39.311,-38.543],[37.465,-40.318],[35.689,-38.472],[36.236,17.008]],"c":true}]},{"i":{"x":0.2,"y":1},"o":{"x":0.4,"y":0},"n":"0p2_1_0p4_0","t":25,"s":[{"i":[[0,0],[0,0],[1.005,-0.008],[-0.008,-1.005],[0,0]],"o":[[0,0],[-0.008,-1.005],[-1.005,0.008],[0,0],[0,0]],"v":[[40.219,17.373],[39.311,-38.543],[37.465,-40.318],[35.689,-38.472],[36.236,17.008]],"c":true}],"e":[{"i":[[0,0],[0,0],[1.005,-0.008],[-0.008,-1.005],[0,0]],"o":[[0,0],[-0.008,-1.005],[-1.005,0.008],[0,0],[0,0]],"v":[[40.219,17.373],[39.311,-38.543],[37.465,-40.318],[35.689,-38.472],[36.236,17.008]],"c":true}]},{"i":{"x":0.2,"y":1},"o":{"x":0.4,"y":0},"n":"0p2_1_0p4_0","t":85,"s":[{"i":[[0,0],[0,0],[1.005,-0.008],[-0.008,-1.005],[0,0]],"o":[[0,0],[-0.008,-1.005],[-1.005,0.008],[0,0],[0,0]],"v":[[40.219,17.373],[39.311,-38.543],[37.465,-40.318],[35.689,-38.472],[36.236,17.008]],"c":true}],"e":[{"i":[[0,0],[0,0],[1,-0.1],[-0.1,-1],[0,0]],"o":[[0,0],[-0.1,-1],[-1,0.1],[0,0],[0,0]],"v":[[40.1,17.3],[34.1,-38.3],[32.1,-39.9],[30.5,-37.9],[36.1,17.3]],"c":true}]},{"t":100}],"ix":2},"hd":false},{"ty":"fl","c":{"a":0,"k":[0.874509811401,0.882352948189,0.898039221764,1],"ix":4},"o":{"a":0,"k":100,"ix":5},"r":1,"hd":false},{"ty":"tr","p":{"a":0,"k":[0,0],"ix":2},"a":{"a":0,"k":[0,0],"ix":1},"s":{"a":0,"k":[100,100],"ix":3},"r":{"a":0,"k":0,"ix":6},"o":{"a":0,"k":100,"ix":7},"sk":{"a":0,"k":0,"ix":4},"sa":{"a":0,"k":0,"ix":5}}],"np":2,"cix":2,"ix":4,"hd":false},{"ty":"gr","it":[{"ind":0,"ty":"sh","ix":1,"ks":{"a":1,"k":[{"i":{"x":0.2,"y":1},"o":{"x":0.4,"y":0},"n":"0p2_1_0p4_0","t":10,"s":[{"i":[[0,0],[0,0],[-1.3,1.8],[0.8,1.4],[0.2,0.1]],"o":[[0,0],[1.8,1.3],[1.1,-1.2],[-2,-3.7],[0,0]],"v":[[26.494,-4.412],[31.4,-0.9],[37,-1.8],[37.4,-6.1],[25.75,-20.225]],"c":true}],"e":[{"i":[[0,0],[0,0],[-0.998,1.983],[1.012,1.256],[0.213,0.067]],"o":[[0,0],[1.983,0.998],[0.896,-1.359],[-2.561,-3.337],[0,0]],"v":[[28.809,-3.523],[34.21,-0.832],[39.597,-2.607],[39.31,-6.916],[25.57,-19.018]],"c":true}]},{"i":{"x":0.2,"y":1},"o":{"x":0.4,"y":0},"n":"0p2_1_0p4_0","t":25,"s":[{"i":[[0,0],[0,0],[-0.998,1.983],[1.012,1.256],[0.213,0.067]],"o":[[0,0],[1.983,0.998],[0.896,-1.359],[-2.561,-3.337],[0,0]],"v":[[28.809,-3.523],[34.21,-0.832],[39.597,-2.607],[39.31,-6.916],[25.57,-19.018]],"c":true}],"e":[{"i":[[0,0],[0,0],[-0.998,1.983],[1.012,1.256],[0.213,0.067]],"o":[[0,0],[1.983,0.998],[0.896,-1.359],[-2.561,-3.337],[0,0]],"v":[[28.809,-3.523],[34.21,-0.832],[39.597,-2.607],[39.31,-6.916],[25.57,-19.018]],"c":true}]},{"i":{"x":0.2,"y":1},"o":{"x":0.4,"y":0},"n":"0p2_1_0p4_0","t":85,"s":[{"i":[[0,0],[0,0],[-0.998,1.983],[1.012,1.256],[0.213,0.067]],"o":[[0,0],[1.983,0.998],[0.896,-1.359],[-2.561,-3.337],[0,0]],"v":[[28.809,-3.523],[34.21,-0.832],[39.597,-2.607],[39.31,-6.916],[25.57,-19.018]],"c":true}],"e":[{"i":[[0,0],[0,0],[-1.3,1.8],[0.8,1.4],[0.2,0.1]],"o":[[0,0],[1.8,1.3],[1.1,-1.2],[-2,-3.7],[0,0]],"v":[[26.494,-4.412],[31.4,-0.9],[37,-1.8],[37.4,-6.1],[25.75,-20.225]],"c":true}]},{"t":100}],"ix":2},"hd":false},{"ty":"fl","c":{"a":0,"k":[0.819607853889,0.886274516582,0.992156863213,1],"ix":4},"o":{"a":0,"k":100,"ix":5},"r":1,"hd":false},{"ty":"tr","p":{"a":0,"k":[0,0],"ix":2},"a":{"a":0,"k":[0,0],"ix":1},"s":{"a":0,"k":[100,100],"ix":3},"r":{"a":0,"k":0,"ix":6},"o":{"a":0,"k":100,"ix":7},"sk":{"a":0,"k":0,"ix":4},"sa":{"a":0,"k":0,"ix":5}}],"np":2,"cix":2,"ix":5,"hd":false}],"ip":0,"op":121,"st":0,"bm":0},{"ddd":0,"ind":4,"ty":4,"sr":1,"ks":{"o":{"a":0,"k":100,"ix":11},"r":{"a":0,"k":0,"ix":10},"p":{"a":0,"k":[182.5,52,0],"ix":2},"a":{"a":0,"k":[2.55,-14.503,0],"ix":1},"s":{"a":0,"k":[100,100,100],"ix":6}},"ao":0,"shapes":[{"ty":"gr","it":[{"ind":0,"ty":"sh","ix":1,"ks":{"a":1,"k":[{"i":{"x":0.2,"y":1},"o":{"x":0.4,"y":0},"n":"0p2_1_0p4_0","t":10,"s":[{"i":[[2.7,0],[0,-2.6],[0,0],[-0.4,0],[0,0.4],[0,0],[-2,0],[0,-1.9],[0,0],[-0.4,0],[0,0.4],[0,0]],"o":[[-2.7,0],[0,0],[0,0.4],[0.4,0],[0,0],[0,-1.9],[2,0],[0,0],[0,0.4],[0.4,0],[0,0],[-0.1,-2.6]],"v":[[-34.8,-3.7],[-39.8,1.1],[-39.8,6],[-39.1,6.7],[-38.4,6],[-38.4,1.1],[-34.8,-2.4],[-31.2,1.1],[-31.2,6],[-30.5,6.7],[-29.8,6],[-29.8,1.1]],"c":true}],"e":[{"i":[[2.7,0],[0,-2.6],[0,0],[-0.4,0],[0,0.4],[0,0],[-2,0],[0,-1.9],[0,0],[-0.4,0],[0,0.4],[0,0]],"o":[[-2.7,0],[0,0],[0,0.4],[0.4,0],[0,0],[0,-1.9],[2,0],[0,0],[0,0.4],[0.4,0],[0,0],[-0.1,-2.6]],"v":[[-33.238,-3.7],[-38.238,1.1],[-38.238,6],[-37.538,6.7],[-36.838,6],[-36.838,1.1],[-33.238,-2.4],[-29.637,1.1],[-29.637,6],[-28.938,6.7],[-28.238,6],[-28.238,1.1]],"c":true}]},{"i":{"x":0.2,"y":1},"o":{"x":0.4,"y":0},"n":"0p2_1_0p4_0","t":25,"s":[{"i":[[2.7,0],[0,-2.6],[0,0],[-0.4,0],[0,0.4],[0,0],[-2,0],[0,-1.9],[0,0],[-0.4,0],[0,0.4],[0,0]],"o":[[-2.7,0],[0,0],[0,0.4],[0.4,0],[0,0],[0,-1.9],[2,0],[0,0],[0,0.4],[0.4,0],[0,0],[-0.1,-2.6]],"v":[[-33.238,-3.7],[-38.238,1.1],[-38.238,6],[-37.538,6.7],[-36.838,6],[-36.838,1.1],[-33.238,-2.4],[-29.637,1.1],[-29.637,6],[-28.938,6.7],[-28.238,6],[-28.238,1.1]],"c":true}],"e":[{"i":[[2.7,0],[0,-2.6],[0,0],[-0.4,0],[0,0.4],[0,0],[-2,0],[0,-1.9],[0,0],[-0.4,0],[0,0.4],[0,0]],"o":[[-2.7,0],[0,0],[0,0.4],[0.4,0],[0,0],[0,-1.9],[2,0],[0,0],[0,0.4],[0.4,0],[0,0],[-0.1,-2.6]],"v":[[-33.238,-3.7],[-38.238,1.1],[-38.238,6],[-37.538,6.7],[-36.838,6],[-36.838,1.1],[-33.238,-2.4],[-29.637,1.1],[-29.637,6],[-28.938,6.7],[-28.238,6],[-28.238,1.1]],"c":true}]},{"i":{"x":0.2,"y":1},"o":{"x":0.4,"y":0},"n":"0p2_1_0p4_0","t":85,"s":[{"i":[[2.7,0],[0,-2.6],[0,0],[-0.4,0],[0,0.4],[0,0],[-2,0],[0,-1.9],[0,0],[-0.4,0],[0,0.4],[0,0]],"o":[[-2.7,0],[0,0],[0,0.4],[0.4,0],[0,0],[0,-1.9],[2,0],[0,0],[0,0.4],[0.4,0],[0,0],[-0.1,-2.6]],"v":[[-33.238,-3.7],[-38.238,1.1],[-38.238,6],[-37.538,6.7],[-36.838,6],[-36.838,1.1],[-33.238,-2.4],[-29.637,1.1],[-29.637,6],[-28.938,6.7],[-28.238,6],[-28.238,1.1]],"c":true}],"e":[{"i":[[2.7,0],[0,-2.6],[0,0],[-0.4,0],[0,0.4],[0,0],[-2,0],[0,-1.9],[0,0],[-0.4,0],[0,0.4],[0,0]],"o":[[-2.7,0],[0,0],[0,0.4],[0.4,0],[0,0],[0,-1.9],[2,0],[0,0],[0,0.4],[0.4,0],[0,0],[-0.1,-2.6]],"v":[[-34.8,-3.7],[-39.8,1.1],[-39.8,6],[-39.1,6.7],[-38.4,6],[-38.4,1.1],[-34.8,-2.4],[-31.2,1.1],[-31.2,6],[-30.5,6.7],[-29.8,6],[-29.8,1.1]],"c":true}]},{"t":100}],"ix":2},"hd":false},{"ty":"fl","c":{"a":0,"k":[0.160784319043,0.176470592618,0.20000000298,1],"ix":4},"o":{"a":0,"k":100,"ix":5},"r":1,"hd":false},{"ty":"tr","p":{"a":0,"k":[0,0],"ix":2},"a":{"a":0,"k":[0,0],"ix":1},"s":{"a":0,"k":[100,100],"ix":3},"r":{"a":0,"k":0,"ix":6},"o":{"a":0,"k":100,"ix":7},"sk":{"a":0,"k":0,"ix":4},"sa":{"a":0,"k":0,"ix":5}}],"np":2,"cix":2,"ix":1,"hd":false},{"ty":"gr","it":[{"ind":0,"ty":"sh","ix":1,"ks":{"a":1,"k":[{"i":{"x":0.2,"y":1},"o":{"x":0.4,"y":0},"n":"0p2_1_0p4_0","t":10,"s":[{"i":[[0.7,0],[0,0],[0,0.8],[0,0],[-0.8,0],[0,0],[0,-0.8],[0,0]],"o":[[0,0],[-0.8,0],[0,0],[0,-0.8],[0,0],[0.8,0],[0,0],[-0.1,0.8]],"v":[[-25.2,9.3],[-44.9,9.3],[-46.3,7.9],[-46.3,5.4],[-44.9,4],[-25.2,4],[-23.8,5.4],[-23.8,7.9]],"c":true}],"e":[{"i":[[0.7,0],[0,0],[0,0.8],[0,0],[-0.8,0],[0,0],[0,-0.8],[0,0]],"o":[[0,0],[-0.8,0],[0,0],[0,-0.8],[0,0],[0.8,0],[0,0],[-0.1,0.8]],"v":[[-23.637,9.3],[-43.337,9.3],[-44.737,7.9],[-44.737,5.4],[-43.337,4],[-23.637,4],[-22.238,5.4],[-22.238,7.9]],"c":true}]},{"i":{"x":0.2,"y":1},"o":{"x":0.4,"y":0},"n":"0p2_1_0p4_0","t":25,"s":[{"i":[[0.7,0],[0,0],[0,0.8],[0,0],[-0.8,0],[0,0],[0,-0.8],[0,0]],"o":[[0,0],[-0.8,0],[0,0],[0,-0.8],[0,0],[0.8,0],[0,0],[-0.1,0.8]],"v":[[-23.637,9.3],[-43.337,9.3],[-44.737,7.9],[-44.737,5.4],[-43.337,4],[-23.637,4],[-22.238,5.4],[-22.238,7.9]],"c":true}],"e":[{"i":[[0.7,0],[0,0],[0,0.8],[0,0],[-0.8,0],[0,0],[0,-0.8],[0,0]],"o":[[0,0],[-0.8,0],[0,0],[0,-0.8],[0,0],[0.8,0],[0,0],[-0.1,0.8]],"v":[[-23.637,9.3],[-43.337,9.3],[-44.737,7.9],[-44.737,5.4],[-43.337,4],[-23.637,4],[-22.238,5.4],[-22.238,7.9]],"c":true}]},{"i":{"x":0.2,"y":1},"o":{"x":0.4,"y":0},"n":"0p2_1_0p4_0","t":85,"s":[{"i":[[0.7,0],[0,0],[0,0.8],[0,0],[-0.8,0],[0,0],[0,-0.8],[0,0]],"o":[[0,0],[-0.8,0],[0,0],[0,-0.8],[0,0],[0.8,0],[0,0],[-0.1,0.8]],"v":[[-23.637,9.3],[-43.337,9.3],[-44.737,7.9],[-44.737,5.4],[-43.337,4],[-23.637,4],[-22.238,5.4],[-22.238,7.9]],"c":true}],"e":[{"i":[[0.7,0],[0,0],[0,0.8],[0,0],[-0.8,0],[0,0],[0,-0.8],[0,0]],"o":[[0,0],[-0.8,0],[0,0],[0,-0.8],[0,0],[0.8,0],[0,0],[-0.1,0.8]],"v":[[-25.2,9.3],[-44.9,9.3],[-46.3,7.9],[-46.3,5.4],[-44.9,4],[-25.2,4],[-23.8,5.4],[-23.8,7.9]],"c":true}]},{"t":100}],"ix":2},"hd":false},{"ty":"fl","c":{"a":0,"k":[0.964705884457,0.40000000596,0.219607844949,1],"ix":4},"o":{"a":0,"k":100,"ix":5},"r":1,"hd":false},{"ty":"tr","p":{"a":0,"k":[0,0],"ix":2},"a":{"a":0,"k":[0,0],"ix":1},"s":{"a":0,"k":[100,100],"ix":3},"r":{"a":0,"k":0,"ix":6},"o":{"a":0,"k":100,"ix":7},"sk":{"a":0,"k":0,"ix":4},"sa":{"a":0,"k":0,"ix":5}}],"np":2,"cix":2,"ix":2,"hd":false},{"ty":"gr","it":[{"ind":0,"ty":"sh","ix":1,"ks":{"a":1,"k":[{"i":{"x":0.2,"y":1},"o":{"x":0.4,"y":0},"n":"0p2_1_0p4_0","t":10,"s":[{"i":[[0,0],[0,0],[0,0],[0,0],[0,0],[0,0],[0,0],[0,0],[0,0],[0,0],[0,0]],"o":[[0,0],[0,0],[0,0],[0,0],[0,0],[0,0],[0,0],[0,0],[0,0],[0,0],[0,0]],"v":[[-31.7,7.9],[-31.7,7],[-35.1,7.5],[-38.5,7],[-38.5,7.9],[-45.2,8.8],[-43.8,24.7],[-38.5,24.7],[-31.7,24.7],[-26.4,24.7],[-25,8.8]],"c":true}],"e":[{"i":[[0,0],[0,0],[0,0],[0,0],[0,0],[0,0],[0,0],[0,0],[0,0],[0,0],[0,0]],"o":[[0,0],[0,0],[0,0],[0,0],[0,0],[0,0],[0,0],[0,0],[0,0],[0,0],[0,0]],"v":[[-30.137,7.9],[-30.137,7],[-33.538,7.5],[-36.938,7],[-36.938,7.9],[-43.637,8.8],[-42.238,24.7],[-36.938,24.7],[-30.137,24.7],[-24.837,24.7],[-23.438,8.8]],"c":true}]},{"i":{"x":0.2,"y":1},"o":{"x":0.4,"y":0},"n":"0p2_1_0p4_0","t":25,"s":[{"i":[[0,0],[0,0],[0,0],[0,0],[0,0],[0,0],[0,0],[0,0],[0,0],[0,0],[0,0]],"o":[[0,0],[0,0],[0,0],[0,0],[0,0],[0,0],[0,0],[0,0],[0,0],[0,0],[0,0]],"v":[[-30.137,7.9],[-30.137,7],[-33.538,7.5],[-36.938,7],[-36.938,7.9],[-43.637,8.8],[-42.238,24.7],[-36.938,24.7],[-30.137,24.7],[-24.837,24.7],[-23.438,8.8]],"c":true}],"e":[{"i":[[0,0],[0,0],[0,0],[0,0],[0,0],[0,0],[0,0],[0,0],[0,0],[0,0],[0,0]],"o":[[0,0],[0,0],[0,0],[0,0],[0,0],[0,0],[0,0],[0,0],[0,0],[0,0],[0,0]],"v":[[-30.137,7.9],[-30.137,7],[-33.538,7.5],[-36.938,7],[-36.938,7.9],[-43.637,8.8],[-42.238,24.7],[-36.938,24.7],[-30.137,24.7],[-24.837,24.7],[-23.438,8.8]],"c":true}]},{"i":{"x":0.2,"y":1},"o":{"x":0.4,"y":0},"n":"0p2_1_0p4_0","t":85,"s":[{"i":[[0,0],[0,0],[0,0],[0,0],[0,0],[0,0],[0,0],[0,0],[0,0],[0,0],[0,0]],"o":[[0,0],[0,0],[0,0],[0,0],[0,0],[0,0],[0,0],[0,0],[0,0],[0,0],[0,0]],"v":[[-30.137,7.9],[-30.137,7],[-33.538,7.5],[-36.938,7],[-36.938,7.9],[-43.637,8.8],[-42.238,24.7],[-36.938,24.7],[-30.137,24.7],[-24.837,24.7],[-23.438,8.8]],"c":true}],"e":[{"i":[[0,0],[0,0],[0,0],[0,0],[0,0],[0,0],[0,0],[0,0],[0,0],[0,0],[0,0]],"o":[[0,0],[0,0],[0,0],[0,0],[0,0],[0,0],[0,0],[0,0],[0,0],[0,0],[0,0]],"v":[[-31.7,7.9],[-31.7,7],[-35.1,7.5],[-38.5,7],[-38.5,7.9],[-45.2,8.8],[-43.8,24.7],[-38.5,24.7],[-31.7,24.7],[-26.4,24.7],[-25,8.8]],"c":true}]},{"t":100}],"ix":2},"hd":false},{"ty":"fl","c":{"a":0,"k":[0.992156863213,0.792156875134,0.250980407,1],"ix":4},"o":{"a":0,"k":100,"ix":5},"r":1,"hd":false},{"ty":"tr","p":{"a":0,"k":[0,0],"ix":2},"a":{"a":0,"k":[0,0],"ix":1},"s":{"a":0,"k":[100,100],"ix":3},"r":{"a":0,"k":0,"ix":6},"o":{"a":0,"k":100,"ix":7},"sk":{"a":0,"k":0,"ix":4},"sa":{"a":0,"k":0,"ix":5}}],"np":2,"cix":2,"ix":3,"hd":false},{"ty":"gr","it":[{"ind":0,"ty":"sh","ix":1,"ks":{"a":1,"k":[{"i":{"x":0.2,"y":1},"o":{"x":0.4,"y":0},"n":"0p2_1_0p4_0","t":10,"s":[{"i":[[0.1,0],[0.1,0.6],[0,0],[-0.2,0.7],[-0.7,-0.2],[-0.9,-4.9],[0.7,-0.1]],"o":[[-0.6,0],[-0.6,-3.5],[-0.7,-0.2],[0.2,-0.7],[0.2,0.1],[0.1,0.7],[-0.1,0.1]],"v":[[20.3,-23.4],[19.1,-24.4],[15.5,-29],[14.7,-30.6],[16.3,-31.4],[21.6,-24.9],[20.6,-23.5]],"c":true}],"e":[{"i":[[0.1,0],[0.1,0.6],[0,0],[-0.2,0.7],[-0.7,-0.2],[-0.9,-4.9],[0.7,-0.1]],"o":[[-0.6,0],[-0.6,-3.5],[-0.7,-0.2],[0.2,-0.7],[0.2,0.1],[0.1,0.7],[-0.1,0.1]],"v":[[24.207,-22.15],[23.007,-23.15],[19.407,-27.75],[18.607,-29.35],[20.207,-30.15],[25.507,-23.65],[24.507,-22.25]],"c":true}]},{"i":{"x":0.2,"y":1},"o":{"x":0.4,"y":0},"n":"0p2_1_0p4_0","t":35,"s":[{"i":[[0.1,0],[0.1,0.6],[0,0],[-0.2,0.7],[-0.7,-0.2],[-0.9,-4.9],[0.7,-0.1]],"o":[[-0.6,0],[-0.6,-3.5],[-0.7,-0.2],[0.2,-0.7],[0.2,0.1],[0.1,0.7],[-0.1,0.1]],"v":[[24.207,-22.15],[23.007,-23.15],[19.407,-27.75],[18.607,-29.35],[20.207,-30.15],[25.507,-23.65],[24.507,-22.25]],"c":true}],"e":[{"i":[[0.1,0],[0.1,0.6],[0,0],[-0.2,0.7],[-0.7,-0.2],[-0.9,-4.9],[0.7,-0.1]],"o":[[-0.6,0],[-0.6,-3.5],[-0.7,-0.2],[0.2,-0.7],[0.2,0.1],[0.1,0.7],[-0.1,0.1]],"v":[[24.207,-22.15],[23.007,-23.15],[19.407,-27.75],[18.607,-29.35],[20.207,-30.15],[25.507,-23.65],[24.507,-22.25]],"c":true}]},{"i":{"x":0.2,"y":1},"o":{"x":0.4,"y":0},"n":"0p2_1_0p4_0","t":85,"s":[{"i":[[0.1,0],[0.1,0.6],[0,0],[-0.2,0.7],[-0.7,-0.2],[-0.9,-4.9],[0.7,-0.1]],"o":[[-0.6,0],[-0.6,-3.5],[-0.7,-0.2],[0.2,-0.7],[0.2,0.1],[0.1,0.7],[-0.1,0.1]],"v":[[24.207,-22.15],[23.007,-23.15],[19.407,-27.75],[18.607,-29.35],[20.207,-30.15],[25.507,-23.65],[24.507,-22.25]],"c":true}],"e":[{"i":[[0.1,0],[0.1,0.6],[0,0],[-0.2,0.7],[-0.7,-0.2],[-0.9,-4.9],[0.7,-0.1]],"o":[[-0.6,0],[-0.6,-3.5],[-0.7,-0.2],[0.2,-0.7],[0.2,0.1],[0.1,0.7],[-0.1,0.1]],"v":[[20.3,-23.4],[19.1,-24.4],[15.5,-29],[14.7,-30.6],[16.3,-31.4],[21.6,-24.9],[20.6,-23.5]],"c":true}]},{"t":100}],"ix":2},"hd":false},{"ty":"fl","c":{"a":0,"k":[0.890196084976,0.949019610882,0.992156863213,1],"ix":4},"o":{"a":1,"k":[{"i":{"x":[0.833],"y":[0.833]},"o":{"x":[0.333],"y":[0]},"n":["0p833_0p833_0p333_0"],"t":10,"s":[100],"e":[0]},{"i":{"x":[0.833],"y":[0.833]},"o":{"x":[0.167],"y":[0.167]},"n":["0p833_0p833_0p167_0p167"],"t":15,"s":[0],"e":[0]},{"i":{"x":[0.667],"y":[1]},"o":{"x":[0.167],"y":[0.167]},"n":["0p667_1_0p167_0p167"],"t":85,"s":[0],"e":[100]},{"t":95}],"ix":5},"r":1,"hd":false},{"ty":"tr","p":{"a":0,"k":[0,0],"ix":2},"a":{"a":0,"k":[0,0],"ix":1},"s":{"a":0,"k":[100,100],"ix":3},"r":{"a":0,"k":0,"ix":6},"o":{"a":0,"k":100,"ix":7},"sk":{"a":0,"k":0,"ix":4},"sa":{"a":0,"k":0,"ix":5}}],"np":2,"cix":2,"ix":4,"hd":false},{"ty":"gr","it":[{"ind":0,"ty":"sh","ix":1,"ks":{"a":1,"k":[{"i":{"x":0.2,"y":1},"o":{"x":0.4,"y":0},"n":"0p2_1_0p4_0","t":10,"s":[{"i":[[0,0],[0.7,1.6],[10.9,0],[3.8,-9.4],[0.4,-1.6],[2,-3.7],[-0.9,-1.2],[-1.8,1.3],[0,0],[0,0],[0,0],[-5.3,-1.7],[-0.6,-1.3],[-1.5,0],[0,2.2],[0,0],[-2,0],[-2.3,0.3],[0,0],[-2,0],[-0.7,1.4],[-0.8,2.7],[-0.8,2.7],[0,0],[-0.9,4.8]],"o":[[-0.4,-1.6],[-3.9,-9.3],[-10.8,0],[-0.7,1.7],[-0.1,0.1],[-0.7,1.4],[1.3,1.8],[0,0],[0.8,4.8],[0,0],[0.9,3.1],[0.7,2.5],[0.6,1.4],[2,0],[0,0],[1.9,0.2],[2.6,0],[0,0],[0,2.2],[1.4,0],[0.6,-1.4],[4.4,-1.7],[0,0],[0,0],[0,0]],"v":[[28,-17.7],[26.4,-22.6],[1.3,-38.7],[-23.7,-22.6],[-25.3,-17.7],[-34.7,-6.1],[-34.4,-1.8],[-28.8,-0.9],[-25.7,-3.1],[-23.4,4.8],[-23.4,4.8],[-13.5,12.3],[-11.5,18.4],[-8.1,20.7],[-4.5,16.6],[-4.5,14.2],[1.3,14.5],[8.6,14],[8.6,16.6],[12.2,20.7],[15.6,18.4],[17.8,11.7],[26,4.8],[26,4.8],[28.3,-3.1]],"c":true}],"e":[{"i":[[0,0],[0.574,1.65],[10.867,0.847],[4.577,-9.047],[0.4,-1.6],[2,-3.7],[-0.9,-1.2],[-1.8,1.3],[0,0],[0,0],[0,0],[-5.152,-2.107],[-0.6,-1.3],[-1.5,0],[0,2.2],[0,0],[-1.994,-0.155],[-2.316,0.12],[0,0],[-2,0],[-0.7,1.4],[-1.007,2.63],[-1.007,2.63],[0,0],[-1.27,4.716]],"o":[[-0.274,-1.626],[-3.166,-9.575],[-10.767,-0.839],[-0.83,1.64],[-0.1,0.1],[-0.7,1.4],[1.3,1.8],[0,0],[2.625,4.847],[0,0],[1.575,3.072],[0.504,2.547],[0.6,1.4],[2,0],[0,0],[1.879,0.347],[2.592,0.202],[0,0],[0,2.2],[1.4,0],[0.6,-1.4],[4.519,-1.353],[0,0],[0,0],[0,0]],"v":[[31.243,-15.659],[30.028,-20.668],[6.255,-38.67],[-19.92,-24.56],[-23.738,-17.7],[-33.138,-6.1],[-32.838,-1.8],[-27.238,-0.9],[-24.137,-3.1],[-20.187,2.78],[-20.087,3.3],[-12.462,11.026],[-11.5,18.4],[-8.1,20.7],[-4.5,16.6],[-3.637,13.62],[2.122,14.37],[9.439,14.438],[8.6,16.6],[12.2,20.7],[15.6,18.4],[18.79,12.86],[27.501,6.618],[27.501,6.618],[30.408,-1.08]],"c":true}]},{"i":{"x":0.2,"y":1},"o":{"x":0.4,"y":0},"n":"0p2_1_0p4_0","t":35,"s":[{"i":[[0,0],[0.574,1.65],[10.867,0.847],[4.577,-9.047],[0.4,-1.6],[2,-3.7],[-0.9,-1.2],[-1.8,1.3],[0,0],[0,0],[0,0],[-5.152,-2.107],[-0.6,-1.3],[-1.5,0],[0,2.2],[0,0],[-1.994,-0.155],[-2.316,0.12],[0,0],[-2,0],[-0.7,1.4],[-1.007,2.63],[-1.007,2.63],[0,0],[-1.27,4.716]],"o":[[-0.274,-1.626],[-3.166,-9.575],[-10.767,-0.839],[-0.83,1.64],[-0.1,0.1],[-0.7,1.4],[1.3,1.8],[0,0],[2.625,4.847],[0,0],[1.575,3.072],[0.504,2.547],[0.6,1.4],[2,0],[0,0],[1.879,0.347],[2.592,0.202],[0,0],[0,2.2],[1.4,0],[0.6,-1.4],[4.519,-1.353],[0,0],[0,0],[0,0]],"v":[[31.243,-15.659],[30.028,-20.668],[6.255,-38.67],[-19.92,-24.56],[-23.738,-17.7],[-33.138,-6.1],[-32.838,-1.8],[-27.238,-0.9],[-24.137,-3.1],[-20.187,2.78],[-20.087,3.3],[-12.462,11.026],[-11.5,18.4],[-8.1,20.7],[-4.5,16.6],[-3.637,13.62],[2.122,14.37],[9.439,14.438],[8.6,16.6],[12.2,20.7],[15.6,18.4],[18.79,12.86],[27.501,6.618],[27.501,6.618],[30.408,-1.08]],"c":true}],"e":[{"i":[[0,0],[0.574,1.65],[10.867,0.847],[4.577,-9.047],[0.4,-1.6],[2,-3.7],[-0.9,-1.2],[-1.8,1.3],[0,0],[0,0],[0,0],[-5.152,-2.107],[-0.6,-1.3],[-1.5,0],[0,2.2],[0,0],[-1.994,-0.155],[-2.316,0.12],[0,0],[-2,0],[-0.7,1.4],[-1.007,2.63],[-1.007,2.63],[0,0],[-1.27,4.716]],"o":[[-0.274,-1.626],[-3.166,-9.575],[-10.767,-0.839],[-0.83,1.64],[-0.1,0.1],[-0.7,1.4],[1.3,1.8],[0,0],[2.625,4.847],[0,0],[1.575,3.072],[0.504,2.547],[0.6,1.4],[2,0],[0,0],[1.879,0.347],[2.592,0.202],[0,0],[0,2.2],[1.4,0],[0.6,-1.4],[4.519,-1.353],[0,0],[0,0],[0,0]],"v":[[31.243,-15.659],[30.028,-20.668],[6.255,-38.67],[-19.92,-24.56],[-23.738,-17.7],[-33.138,-6.1],[-32.838,-1.8],[-27.238,-0.9],[-24.137,-3.1],[-20.187,2.78],[-20.087,3.3],[-12.462,11.026],[-11.5,18.4],[-8.1,20.7],[-4.5,16.6],[-3.637,13.62],[2.122,14.37],[9.439,14.438],[8.6,16.6],[12.2,20.7],[15.6,18.4],[18.79,12.86],[27.501,6.618],[27.501,6.618],[30.408,-1.08]],"c":true}]},{"i":{"x":0.2,"y":1},"o":{"x":0.4,"y":0},"n":"0p2_1_0p4_0","t":85,"s":[{"i":[[0,0],[0.574,1.65],[10.867,0.847],[4.577,-9.047],[0.4,-1.6],[2,-3.7],[-0.9,-1.2],[-1.8,1.3],[0,0],[0,0],[0,0],[-5.152,-2.107],[-0.6,-1.3],[-1.5,0],[0,2.2],[0,0],[-1.994,-0.155],[-2.316,0.12],[0,0],[-2,0],[-0.7,1.4],[-1.007,2.63],[-1.007,2.63],[0,0],[-1.27,4.716]],"o":[[-0.274,-1.626],[-3.166,-9.575],[-10.767,-0.839],[-0.83,1.64],[-0.1,0.1],[-0.7,1.4],[1.3,1.8],[0,0],[2.625,4.847],[0,0],[1.575,3.072],[0.504,2.547],[0.6,1.4],[2,0],[0,0],[1.879,0.347],[2.592,0.202],[0,0],[0,2.2],[1.4,0],[0.6,-1.4],[4.519,-1.353],[0,0],[0,0],[0,0]],"v":[[31.243,-15.659],[30.028,-20.668],[6.255,-38.67],[-19.92,-24.56],[-23.738,-17.7],[-33.138,-6.1],[-32.838,-1.8],[-27.238,-0.9],[-24.137,-3.1],[-20.187,2.78],[-20.087,3.3],[-12.462,11.026],[-11.5,18.4],[-8.1,20.7],[-4.5,16.6],[-3.637,13.62],[2.122,14.37],[9.439,14.438],[8.6,16.6],[12.2,20.7],[15.6,18.4],[18.79,12.86],[27.501,6.618],[27.501,6.618],[30.408,-1.08]],"c":true}],"e":[{"i":[[0,0],[0.7,1.6],[10.9,0],[3.8,-9.4],[0.4,-1.6],[2,-3.7],[-0.9,-1.2],[-1.8,1.3],[0,0],[0,0],[0,0],[-5.3,-1.7],[-0.6,-1.3],[-1.5,0],[0,2.2],[0,0],[-2,0],[-2.3,0.3],[0,0],[-2,0],[-0.7,1.4],[-0.8,2.7],[-0.8,2.7],[0,0],[-0.9,4.8]],"o":[[-0.4,-1.6],[-3.9,-9.3],[-10.8,0],[-0.7,1.7],[-0.1,0.1],[-0.7,1.4],[1.3,1.8],[0,0],[0.8,4.8],[0,0],[0.9,3.1],[0.7,2.5],[0.6,1.4],[2,0],[0,0],[1.9,0.2],[2.6,0],[0,0],[0,2.2],[1.4,0],[0.6,-1.4],[4.4,-1.7],[0,0],[0,0],[0,0]],"v":[[28,-17.7],[26.4,-22.6],[1.3,-38.7],[-23.7,-22.6],[-25.3,-17.7],[-34.7,-6.1],[-34.4,-1.8],[-28.8,-0.9],[-25.7,-3.1],[-23.4,4.8],[-23.4,4.8],[-13.5,12.3],[-11.5,18.4],[-8.1,20.7],[-4.5,16.6],[-4.5,14.2],[1.3,14.5],[8.6,14],[8.6,16.6],[12.2,20.7],[15.6,18.4],[17.8,11.7],[26,4.8],[26,4.8],[28.3,-3.1]],"c":true}]},{"t":100}],"ix":2},"hd":false},{"ty":"fl","c":{"a":0,"k":[0.819607853889,0.886274516582,0.992156863213,1],"ix":4},"o":{"a":0,"k":100,"ix":5},"r":1,"hd":false},{"ty":"tr","p":{"a":0,"k":[0,0],"ix":2},"a":{"a":0,"k":[0,0],"ix":1},"s":{"a":0,"k":[100,100],"ix":3},"r":{"a":0,"k":0,"ix":6},"o":{"a":0,"k":100,"ix":7},"sk":{"a":0,"k":0,"ix":4},"sa":{"a":0,"k":0,"ix":5}}],"np":2,"cix":2,"ix":5,"hd":false},{"ty":"gr","it":[{"d":1,"ty":"el","s":{"a":0,"k":[74.8,12.2],"ix":2},"p":{"a":0,"k":[0,0],"ix":3},"hd":false},{"ty":"fl","c":{"a":0,"k":[0.960784316063,0.960784316063,0.960784316063,1],"ix":4},"o":{"a":0,"k":100,"ix":5},"r":1,"hd":false},{"ty":"tr","p":{"a":1,"k":[{"i":{"x":0.667,"y":1},"o":{"x":0.333,"y":0},"n":"0p667_1_0p333_0","t":10,"s":[1.6,21.9],"e":[4.6,21.9],"to":[0.49999898672104,0],"ti":[-0.49999898672104,0]},{"i":{"x":0.667,"y":0.667},"o":{"x":0.333,"y":0.333},"n":"0p667_0p667_0p333_0p333","t":25,"s":[4.6,21.9],"e":[4.6,21.9],"to":[0,0],"ti":[0,0]},{"i":{"x":0.667,"y":1},"o":{"x":0.333,"y":0},"n":"0p667_1_0p333_0","t":85,"s":[4.6,21.9],"e":[1.6,21.9],"to":[-0.49999898672104,0],"ti":[0.49999898672104,0]},{"t":100}],"ix":2},"a":{"a":0,"k":[0,0],"ix":1},"s":{"a":0,"k":[100,100],"ix":3},"r":{"a":0,"k":0,"ix":6},"o":{"a":0,"k":100,"ix":7},"sk":{"a":0,"k":0,"ix":4},"sa":{"a":0,"k":0,"ix":5}}],"np":2,"cix":2,"ix":6,"hd":false}],"ip":0,"op":121,"st":0,"bm":0},{"ddd":0,"ind":5,"ty":4,"sr":1,"ks":{"o":{"a":0,"k":100,"ix":11},"r":{"a":0,"k":0,"ix":10},"p":{"a":0,"k":[297.95,43.6,0],"ix":2},"a":{"a":0,"k":[117.95,-26.4,0],"ix":1},"s":{"a":0,"k":[100,100,100],"ix":6}},"ao":0,"shapes":[{"ty":"gr","it":[{"ind":0,"ty":"sh","ix":1,"ks":{"a":0,"k":{"i":[[0.6,0],[0,0],[0,0],[0,0],[0,0],[0,0],[0,-0.6],[-0.6,0],[0,0],[0,0.6]],"o":[[0,0],[0,0],[0,0],[0,0],[0,0],[-0.5,0],[0,0.5],[0,0],[0.5,0],[0,-0.5]],"v":[[126.5,2],[118.8,2],[118.8,-32.4],[116.8,-32.4],[116.8,2],[109.3,2],[108.3,3],[109.3,4],[126.5,4],[127.5,3]],"c":true},"ix":2},"hd":false},{"ty":"fl","c":{"a":0,"k":[0.878431379795,0.878431379795,0.878431379795,1],"ix":4},"o":{"a":0,"k":100,"ix":5},"r":1,"hd":false},{"ty":"tr","p":{"a":0,"k":[0,0],"ix":2},"a":{"a":0,"k":[0,0],"ix":1},"s":{"a":0,"k":[100,100],"ix":3},"r":{"a":0,"k":0,"ix":6},"o":{"a":0,"k":100,"ix":7},"sk":{"a":0,"k":0,"ix":4},"sa":{"a":0,"k":0,"ix":5}}],"np":2,"cix":2,"ix":1,"hd":false},{"ty":"gr","it":[{"ind":0,"ty":"sh","ix":1,"ks":{"a":0,"k":{"i":[[0,0],[0,0],[0,0],[0,0]],"o":[[0,0],[0,0],[0,0],[0,0]],"v":[[130.2,-56.8],[105.3,-56.8],[103.5,-32.4],[132.4,-32.4]],"c":true},"ix":2},"hd":false},{"ty":"fl","c":{"a":0,"k":[0.960784316063,0.960784316063,0.960784316063,1],"ix":4},"o":{"a":0,"k":100,"ix":5},"r":1,"hd":false},{"ty":"tr","p":{"a":0,"k":[0,0],"ix":2},"a":{"a":0,"k":[0,0],"ix":1},"s":{"a":0,"k":[100,100],"ix":3},"r":{"a":0,"k":0,"ix":6},"o":{"a":0,"k":100,"ix":7},"sk":{"a":0,"k":0,"ix":4},"sa":{"a":0,"k":0,"ix":5}}],"np":2,"cix":2,"ix":2,"hd":false}],"ip":0,"op":121,"st":0,"bm":0},{"ddd":0,"ind":6,"ty":4,"sr":1,"ks":{"o":{"a":0,"k":100,"ix":11},"r":{"a":0,"k":0,"ix":10},"p":{"a":0,"k":[180,71,0],"ix":2},"a":{"a":0,"k":[0.5,0.3,0],"ix":1},"s":{"a":0,"k":[100,100,100],"ix":6}},"ao":0,"shapes":[{"ty":"gr","it":[{"ty":"rc","d":1,"s":{"a":0,"k":[360,54],"ix":2},"p":{"a":0,"k":[0,0],"ix":3},"r":{"a":0,"k":0,"ix":4},"hd":false},{"ty":"fl","c":{"a":0,"k":[0.992156863213,0.992156863213,0.992156863213,1],"ix":4},"o":{"a":0,"k":100,"ix":5},"r":1,"hd":false},{"ty":"tr","p":{"a":0,"k":[0.5,30.4],"ix":2},"a":{"a":0,"k":[0,0],"ix":1},"s":{"a":0,"k":[100,100],"ix":3},"r":{"a":0,"k":0,"ix":6},"o":{"a":0,"k":100,"ix":7},"sk":{"a":0,"k":0,"ix":4},"sa":{"a":0,"k":0,"ix":5}}],"np":2,"cix":2,"ix":1,"hd":false},{"ty":"gr","it":[{"ind":0,"ty":"sh","ix":1,"ks":{"a":0,"k":{"i":[[3.7,0],[0,-3.6],[0,0],[0.8,0],[0,0],[0.7,-0.2],[0,0],[3.6,0],[0,0],[0,-3.6],[0,0],[-3.6,0],[0,0],[0,0],[0,3.6],[0,0]],"o":[[-3.7,0],[0,0],[-0.7,-0.2],[0,0],[-0.8,0],[0,0],[0,-3.7],[0,0],[-3.7,0],[0,0],[0,3.7],[0,0],[0,0],[3.7,0],[0,0],[0,-3.7]],"v":[[-100.4,-22.7],[-107,-16.1],[-107,-11.9],[-109.3,-12.2],[-129,-12.2],[-131.3,-11.9],[-131.3,-16.1],[-137.9,-22.7],[-137.9,-22.7],[-144.5,-16.1],[-144.5,-3.248],[-137.9,3.352],[-137.9,3.352],[-100.4,3.352],[-93.8,-3.248],[-93.8,-16.1]],"c":true},"ix":2},"hd":false},{"ty":"fl","c":{"a":0,"k":[0.933333337307,0.933333337307,0.933333337307,1],"ix":4},"o":{"a":0,"k":100,"ix":5},"r":1,"hd":false},{"ty":"tr","p":{"a":0,"k":[0,0],"ix":2},"a":{"a":0,"k":[0,0],"ix":1},"s":{"a":0,"k":[100,100],"ix":3},"r":{"a":0,"k":0,"ix":6},"o":{"a":0,"k":100,"ix":7},"sk":{"a":0,"k":0,"ix":4},"sa":{"a":0,"k":0,"ix":5}}],"np":2,"cix":2,"ix":2,"hd":false},{"ty":"gr","it":[{"ind":0,"ty":"sh","ix":1,"ks":{"a":0,"k":{"i":[[4.9,0],[0,0],[0,-4.9],[0,0],[0,0],[0,0]],"o":[[0,0],[-4.9,0],[0,0],[0,0],[0,0],[0,-4.9]],"v":[[-109.3,-29],[-129,-29],[-137.9,-20.1],[-137.9,-11.2],[-100.4,-11.2],[-100.4,-20.1]],"c":true},"ix":2},"hd":false},{"ty":"fl","c":{"a":0,"k":[0.878431379795,0.878431379795,0.878431379795,1],"ix":4},"o":{"a":0,"k":100,"ix":5},"r":1,"hd":false},{"ty":"tr","p":{"a":0,"k":[0,0],"ix":2},"a":{"a":0,"k":[0,0],"ix":1},"s":{"a":0,"k":[100,100],"ix":3},"r":{"a":0,"k":0,"ix":6},"o":{"a":0,"k":100,"ix":7},"sk":{"a":0,"k":0,"ix":4},"sa":{"a":0,"k":0,"ix":5}}],"np":2,"cix":2,"ix":3,"hd":false}],"ip":0,"op":121,"st":0,"bm":0}],"markers":[]}