{
    "release-list": {
        "release": [
            {
                "title": "What I've Done",
                "status": {
                    "_id": "4e304316-386d-3409-af2e-78857eec5cfe",
                    "__text": "Official"
                },
                "quality": "normal",
                "text-representation": {
                    "language": "eng"
                },
                "date": "2007-05-06",
                "country": "XW",
                "release-event-list": {
                    "release-event": {
                        "date": "2007-05-06",
                        "area": {
                            "name": "[Worldwide]",
                            "sort-name": "[Worldwide]",
                            "iso-3166-1-code-list": {
                                "iso-3166-1-code": "XW"
                            },
                            "_id": "525d4e18-3d00-31b9-a58b-a146a916de8f"
                        }
                    },
                    "_count": "1"
                },
                "barcode": "054391998583",
                "cover-art-archive": {
                    "artwork": "true",
                    "count": "1",
                    "front": "true",
                    "back": "false"
                },
                "_id": "8b08b9bb-cedf-42d8-8a43-f1f8a543ddb5"
            },
            {
                "title": "Do I Wanna Know?",
                "status": {
                    "_id": "4e304316-386d-3409-af2e-78857eec5cfe",
                    "__text": "Official"
                },
                "quality": "normal",
                "packaging": {
                    "_id": "119eba76-b343-3e02-a292-f0f00644bb9b",
                    "__text": "None"
                },
                "text-representation": {
                    "language": "eng",
                    "script": "Latn"
                },
                "date": "2013-07-18",
                "country": "GB",
                "release-event-list": {
                    "release-event": {
                        "date": "2013-07-18",
                        "area": {
                            "name": "United Kingdom",
                            "sort-name": "United Kingdom",
                            "iso-3166-1-code-list": {
                                "iso-3166-1-code": "GB"
                            },
                            "_id": "8a754a16-0027-3a29-b6d7-2b40ea0481ed"
                        }
                    },
                    "_count": "1"
                },
                "barcode": "887829054267",
                "asin": "B00E199RJG",
                "cover-art-archive": {
                    "artwork": "true",
                    "count": "1",
                    "front": "true",
                    "back": "false"
                },
                "_id": "37f30c11-3eb1-426a-bfab-ab46a0dc1880"
            },
            {
                "title": "evermore",
                "status": {
                    "_id": "4e304316-386d-3409-af2e-78857eec5cfe",
                    "__text": "Official"
                },
                "quality": "normal",
                "packaging": {
                    "_id": "119eba76-b343-3e02-a292-f0f00644bb9b",
                    "__text": "None"
                },
                "text-representation": {
                    "language": "eng",
                    "script": "Latn"
                },
                "date": "2020-12-11",
                "country": "XW",
                "release-event-list": {
                    "release-event": {
                        "date": "2020-12-11",
                        "area": {
                            "name": "[Worldwide]",
                            "sort-name": "[Worldwide]",
                            "iso-3166-1-code-list": {
                                "iso-3166-1-code": "XW"
                            },
                            "_id": "525d4e18-3d00-31b9-a58b-a146a916de8f"
                        }
                    },
                    "_count": "1"
                },
                "asin": "B08Q8LLD9T",
                "cover-art-archive": {
                    "artwork": "true",
                    "count": "3",
                    "front": "true",
                    "back": "true"
                },
                "_id": "51291562-2794-45c9-9d77-bc1e65888edf"
            }
        ],
        "_count": "3"
    }
}